astrotraders/__init__.py
astrotraders/api/__init__.py
astrotraders/api/client.py
astrotraders/api/exceptions.py
astrotraders/api/resources/__init__.py
astrotraders/api/resources/agents.py
astrotraders/api/resources/base.py
astrotraders/api/resources/contracts.py
astrotraders/api/resources/factions.py
astrotraders/api/resources/fleet.py
astrotraders/api/resources/server.py
astrotraders/api/resources/systems.py
astrotraders/api/schemas.py
astrotraders/api/utils.py
astrotraders/api/wrapper.py
astrotraders/py.typed
astrotraders-1.0.2.dist-info/METADATA
astrotraders-1.0.2.dist-info/WHEEL
astrotraders-1.0.2.dist-info/RECORD
