Metadata-Version: 2.1
Name: astrotraders
Version: 1.0.2
Summary: A typed, handwrited and powerful spacetraders API wrapper
Home-page: https://github.com/kiriharu/astrotraders
Keywords: spacetraders,spacetraders.io
Author: kiriharu
Author-email: me@kiriha.ru
Requires-Python: >=3.10,<4.0
Classifier: Intended Audience :: Developers
Classifier: Programming Language :: Python :: 3
Classifier: Programming Language :: Python :: 3.10
Classifier: Programming Language :: Python :: 3.11
Classifier: Programming Language :: Python :: 3
Classifier: Topic :: Utilities
Classifier: Typing :: Typed
Requires-Dist: httpx (>=0.24.0,<0.25.0)
Requires-Dist: orjson (>=3.8.12,<4.0.0)
Requires-Dist: pydantic (>=1.10.7,<2.0.0)
Project-URL: Repository, https://github.com/kiriharu/astrotraders
